calculate_pd/__init__.py
calculate_pd/calculate_pd.py
distance_matrix/__init__.py
distance_matrix/distance_matrix.py
helpers/__init__.py
helpers/calculate_pd.py
helpers/distance_matrix.py
helpers/sample_rvps.py
pointwise_libs/__init__.py
pointwise_libs/calculate_pd.py
pointwise_libs/distance_matrix.py
pointwise_libs/sample_rvps.py
sample_rvps/__init__.py
sample_rvps/sample_rvps.py
pointwise_libs-0.0.7.dist-info/METADATA
pointwise_libs-0.0.7.dist-info/WHEEL
pointwise_libs-0.0.7.dist-info/top_level.txt
pointwise_libs-0.0.7.dist-info/RECORD
