Metadata-Version: 2.1
Name: pointwise-libs
Version: 0.0.7
Summary: Helper functions for my political science research
Home-page: https://github.com/lieuzhenghong/pointwise-libs
Author: Lieu Zheng Hong
Author-email: lieuzhenghong@gmail.com
License: UNKNOWN
Platform: UNKNOWN
Classifier: Programming Language :: Python :: 3
Classifier: License :: OSI Approved :: MIT License
Classifier: Operating System :: OS Independent
Requires-Python: >=3.6
Requires-Dist: docopt
Requires-Dist: requests
Requires-Dist: geopandas
Requires-Dist: numpy
Requires-Dist: pandas
Requires-Dist: scipy
